pyprotodef/__init__.py
pyprotodef/protodef.py
pyprotodef-0.1.0.dist-info/LICENSE
pyprotodef-0.1.0.dist-info/METADATA
pyprotodef-0.1.0.dist-info/WHEEL
pyprotodef-0.1.0.dist-info/top_level.txt
pyprotodef-0.1.0.dist-info/RECORD
