Metadata-Version: 2.2
Name: pyprotodef
Version: 0.1.0
Summary: A lightweight binary protocol serialization library like ProtoDef but in Python.
Home-page: https://github.com/alchemist123/pyprotodef
Author: Amal v s
Author-email: amal.vs.engineer@gmail.com
Classifier: Programming Language :: Python :: 3
Classifier: License :: OSI Approved :: MIT License
Classifier: Operating System :: OS Independent
Requires-Python: >=3.6
License-File: LICENSE
Dynamic: author
Dynamic: author-email
Dynamic: classifier
Dynamic: description
Dynamic: description-content-type
Dynamic: home-page
Dynamic: requires-python
Dynamic: summary
